pydantic_mcp/__init__.py
pydantic_mcp/py.typed
pydantic_mcp-0.1.1.dist-info/METADATA
pydantic_mcp-0.1.1.dist-info/WHEEL
pydantic_mcp-0.1.1.dist-info/licenses/LICENSE
pydantic_mcp-0.1.1.dist-info/RECORD
