Metadata-Version: 2.4
Name: pydantic-mcp
Version: 0.1.1
Summary: Model Context Protocol tool calling support for Pydantic AI
Project-URL: Repository, https://github.com/rectalogic/pydantic-mcp
Project-URL: Issues, https://github.com/rectalogic/pydantic-mcp/issues
Project-URL: Related, https://modelcontextprotocol.io/
Author-email: Andrew Wason <rectalogic@rectalogic.com>
License-File: LICENSE
Classifier: License :: OSI Approved :: MIT License
Requires-Python: >=3.10
Requires-Dist: mcp~=1.0
Requires-Dist: pydantic-ai>=0.0.35
Requires-Dist: pydantic~=2.10
Requires-Dist: typing-extensions~=4.12
